{
  "BurstVersion": "12fd8c57-ac57-41e8-88f3-e2a61ac3563b",
  "Assemblies": [
    {
      "FullName": "Unity.Burst, Version=0.0.0.0, Culture=neutral, PublicKeyToken=null",
      "LastWriteTime": "2021-09-18T23:39:40.0959788Z"
    },
    {
      "FullName": "mscorlib, Version=4.0.0.0, Culture=neutral, PublicKeyToken=b77a5c561934e089",
      "LastWriteTime": "2021-05-01T16:33:10Z"
    },
    {
      "FullName": "UnityEngine.AnimationModule, Version=0.0.0.0, Culture=neutral, PublicKeyToken=null",
      "LastWriteTime": "2021-05-01T16:39:10Z"
    },
    {
      "FullName": "Unity.Animation.Rigging, Version=0.0.0.0, Culture=neutral, PublicKeyToken=null",
      "LastWriteTime": "2021-09-18T23:39:41.2037201Z"
    },
    {
      "FullName": "mscorlib, Version=2.0.0.0, Culture=neutral, PublicKeyToken=b77a5c561934e089",
      "LastWriteTime": "2021-05-01T16:33:10Z"
    },
    {
      "FullName": "UnityEngine.CoreModule, Version=0.0.0.0, Culture=neutral, PublicKeyToken=null",
      "LastWriteTime": "2021-05-01T16:39:04Z"
    }
  ],
  "Functions": [
    {
      "FullName": "System.Int32 Unity.Burst.Intrinsics.X86::DoGetCSRTrampoline()",
      "ModuleOptionsHash": 8794384452606821980,
      "ModuleHash": "e0fe67c625cddf39b06bfe91da7147fa",
      "LinkName": "CDCA4A5193BE5947",
      "AssemblyDependencyIndices": [
        0,
        1
      ]
    },
    {
      "FullName": "System.Void Unity.Burst.Intrinsics.X86::DoSetCSRTrampoline(System.Int32)",
      "ModuleOptionsHash": 8794384452606821980,
      "ModuleHash": "998a5e3af6d121a970fd4d6f0a936b8b",
      "LinkName": "801E9A000BB37B05",
      "AssemblyDependencyIndices": [
        0,
        1
      ]
    },
    {
      "FullName": "System.Void UnityEngine.Animations.ProcessAnimationJobStruct`1<UnityEngine.Animations.Rigging.TwoBoneIKConstraintJob>::Execute(T&,System.IntPtr,System.IntPtr,Unity.Jobs.LowLevel.Unsafe.JobRanges&,System.Int32)",
      "ModuleOptionsHash": 8794384452606821980,
      "ModuleHash": "d71d80cced16f21fd08c8401a9386897",
      "LinkName": "9F5ECC376B551731",
      "AssemblyDependencyIndices": [
        2,
        3,
        4,
        5,
        1
      ]
    },
    {
      "FullName": "System.Void UnityEngine.Animations.ProcessAnimationJobStruct`1<UnityEngine.Animations.Rigging.MultiAimConstraintJob>::Execute(T&,System.IntPtr,System.IntPtr,Unity.Jobs.LowLevel.Unsafe.JobRanges&,System.Int32)",
      "ModuleOptionsHash": 8794384452606821980,
      "ModuleHash": "39f95111d79e09cb2beefdc3ff490bcf",
      "LinkName": "FCB60251D6B64A75",
      "AssemblyDependencyIndices": [
        2,
        3,
        4,
        5,
        1
      ]
    },
    {
      "FullName": "System.Void UnityEngine.Animations.ProcessAnimationJobStruct`1<UnityEngine.Animations.Rigging.RigSyncSceneToStreamJob>::Execute(T&,System.IntPtr,System.IntPtr,Unity.Jobs.LowLevel.Unsafe.JobRanges&,System.Int32)",
      "ModuleOptionsHash": 8794384452606821980,
      "ModuleHash": "3b08f1cd51fe37952bcc8c44736cdd44",
      "LinkName": "BC91ACAA17E251EE",
      "AssemblyDependencyIndices": [
        2,
        3,
        4,
        5,
        1
      ]
    }
  ]
}